mesofield/__init__.py
mesofield/_reader.py
mesofield/_sample_data.py
mesofield/_version.py
mesofield/_widget.py
mesofield/_writer.py
mesofield/napari.yaml
mesofield/_tests/__init__.py
mesofield/_tests/test_reader.py
mesofield/_tests/test_sample_data.py
mesofield/_tests/test_widget.py
mesofield/_tests/test_writer.py
napari_mesofield-0.1.0.dist-info/LICENSE
napari_mesofield-0.1.0.dist-info/METADATA
napari_mesofield-0.1.0.dist-info/WHEEL
napari_mesofield-0.1.0.dist-info/entry_points.txt
napari_mesofield-0.1.0.dist-info/top_level.txt
napari_mesofield-0.1.0.dist-info/RECORD
