Metadata-Version: 2.1
Name: napari-mesofield
Version: 0.1.0
Summary: A plugin that extends napari functionality as an image acquisition software to automate multi-modal experimental control, setup, and analysis for mesoscopic widefield acquistion of 1P epiflourescent signals in the mouse cortex.
Author: Jacob Gronemeyer
Author-email: jgronemeyer@psu.edu
License: 
Project-URL: Bug Tracker, https://github.com/Gronemeyer/napari-mesofield/issues
Project-URL: Documentation, https://github.com/Gronemeyer/napari-mesofield#README.md
Project-URL: Source Code, https://github.com/Gronemeyer/napari-mesofield
Project-URL: User Support, https://github.com/Gronemeyer/napari-mesofield/issues
Classifier: Development Status :: 2 - Pre-Alpha
Classifier: Framework :: napari
Classifier: Intended Audience :: Developers
Classifier: License :: OSI Approved :: Mozilla Public License 2.0 (MPL 2.0)
Classifier: Operating System :: OS Independent
Classifier: Programming Language :: Python
Classifier: Programming Language :: Python :: 3
Classifier: Programming Language :: Python :: 3 :: Only
Classifier: Programming Language :: Python :: 3.9
Classifier: Programming Language :: Python :: 3.10
Classifier: Programming Language :: Python :: 3.11
Classifier: Programming Language :: Python :: 3.12
Classifier: Topic :: Scientific/Engineering :: Image Processing
Requires-Python: >=3.9
License-File: LICENSE
Requires-Dist: numpy
Requires-Dist: magicgui
Requires-Dist: qtpy
Requires-Dist: scikit-image
Provides-Extra: testing
Requires-Dist: tox ; extra == 'testing'
Requires-Dist: pytest ; extra == 'testing'
Requires-Dist: pytest-cov ; extra == 'testing'
Requires-Dist: pytest-qt ; extra == 'testing'
Requires-Dist: napari ; extra == 'testing'
Requires-Dist: pyqt5 ; extra == 'testing'
